file_picker_py-0.2.0.dist-info/METADATA
file_picker_py-0.2.0.dist-info/WHEEL
file_picker_py/file_picker_py.pyi
file_picker_py/py.typed
file_picker_py/__init__.py
file_picker_py/file_picker_py.pyd
file_picker_py-0.2.0.dist-info/RECORD
